{
  "name": "posmv_input_plugin",
  "versions": {
    "1.0.0": {
      "server@stable": {
        "tested": "2026-04-28T05:19:43.449Z",
        "triggered_by": "schema_change",
        "node_version": "24",
        "server_version": "2.26.0",
        "installs": true,
        "loads": true,
        "activates": true,
        "activates_without_config": true,
        "detected_providers": [],
        "unstubbed_accesses": [],
        "has_schema": true,
        "has_own_tests": false,
        "own_tests_pass": false,
        "tests_runnable": false,
        "has_install_scripts": false,
        "has_changelog": false,
        "has_screenshots": false,
        "audit_critical": 0,
        "audit_high": 0,
        "audit_moderate": 0,
        "composite": 55,
        "badges": [
          "compatible",
          "loads",
          "activates",
          "npm-audit-ok",
          "no-plugin-ci"
        ],
        "test_status": "none"
      }
    }
  },
  "stars": 0,
  "open_issues": 0,
  "contributors": 1,
  "github_url": "https://github.com/magnuan/signalK_posmv_input_plugin",
  "plugin_ci": {
    "status": "no-run",
    "head_sha": "3e7f71679aab942319e4caac86a704e4882ddd67",
    "commit_url": "https://github.com/magnuan/signalK_posmv_input_plugin/commit/3e7f71679aab942319e4caac86a704e4882ddd67"
  }
}
